wormneuroatlas/CellLineage.py
wormneuroatlas/Cengen.py
wormneuroatlas/ExponentialConvolution_min.py
wormneuroatlas/NeuroAtlas.py
wormneuroatlas/PeptideGPCR.py
wormneuroatlas/SynapseSign.py
wormneuroatlas/WormBase.py
wormneuroatlas/__init__.py
wormneuroatlas/data/GenesExpressing-daf-2-thrs2.csv
wormneuroatlas/data/GenesExpressing-neuropeptide-receptors.csv
wormneuroatlas/data/GenesExpressing-neuropeptides.csv
wormneuroatlas/data/GenesExpressing-npr-11-thrs2.csv
wormneuroatlas/data/GenesExpressing-npr-4-thrs2.csv
wormneuroatlas/data/GenesExpressing-pdfr-1-thrs2.csv
wormneuroatlas/data/GenesExpressing-unc-7-unc-9-inx-_-eat-5-thrs2.csv
wormneuroatlas/data/SEE_README_FOR_CITATIONS
wormneuroatlas/data/aconnectome.json
wormneuroatlas/data/aconnectome_default.h5
wormneuroatlas/data/aconnectome_ids_ganglia.json
wormneuroatlas/data/aconnectome_white_1986_A.csv
wormneuroatlas/data/aconnectome_white_1986_L4.csv
wormneuroatlas/data/aconnectome_white_1986_whole.csv
wormneuroatlas/data/aconnectome_witvliet_2020_7.csv
wormneuroatlas/data/aconnectome_witvliet_2020_8.csv
wormneuroatlas/data/anatlas_neuron_positions.txt
wormneuroatlas/data/c_elegans.PRJNA13758.WS286.geneIDs.txt
wormneuroatlas/data/cached_seq_ids.txt
wormneuroatlas/data/cell_lineage.txt
wormneuroatlas/data/cengen.h5
wormneuroatlas/data/cengen_021821_conservative_threshold3.csv
wormneuroatlas/data/cengen_021821_liberal_threshold1.csv
wormneuroatlas/data/cengen_021821_medium_threshold2.csv
wormneuroatlas/data/cengen_021821_stringent_threshold4.csv
wormneuroatlas/data/deorphanization_media_6.csv
wormneuroatlas/data/esconnectome_monoamines_Bentley_2016.csv
wormneuroatlas/data/esconnectome_neuropeptides_Bentley_2016.csv
wormneuroatlas/data/froonikcx_peptide_gpcr.txt
wormneuroatlas/data/funatlas.h5
wormneuroatlas/data/journal.pcbi.1007974.s003.xlsx
wormneuroatlas/data/neuron_ids.txt
wormneuroatlas-0.0.7.3.dist-info/LICENSE
wormneuroatlas-0.0.7.3.dist-info/METADATA
wormneuroatlas-0.0.7.3.dist-info/WHEEL
wormneuroatlas-0.0.7.3.dist-info/top_level.txt
wormneuroatlas-0.0.7.3.dist-info/RECORD
