Metadata-Version: 2.1
Name: wormneuroatlas
Version: 0.0.7.3
Summary: A Python package combining multimodal C. elegans’ neural datasets
Home-page: https://github.com/francescorandi/wormneuroatlas
Author: Francesco Randi
Author-email: Francesco Randi <francesco.randi@gmail.com>
Project-URL: Homepage, https://github.com/francescorandi/wormneuroatlas
Project-URL: Documentation, https://francescorandi.github.io/wormneuroatlas
Project-URL: Reference, https://url.to.paper
Project-URL: Bug Tracker, https://github.com/francescorandi/wormneuroatlas/issues
Classifier: Programming Language :: Python :: 3
Classifier: License :: OSI Approved :: GNU General Public License v3 or later (GPLv3+)
Classifier: Operating System :: OS Independent
Requires-Python: >=3.7
License-File: LICENSE
Requires-Dist: numpy
Requires-Dist: scipy
Requires-Dist: matplotlib
Requires-Dist: urllib3
Requires-Dist: h5py
Requires-Dist: pdoc
Requires-Dist: pandas
Requires-Dist: openpyxl
